PySALESetup/__init__.py
PySALESetup/_version.py
PySALESetup/constants.py
PySALESetup/creation.py
PySALESetup/functions.py
PySALESetup/grain_library.py
PySALESetup/input_files.py
PySALESetup/mesh.py
PySALESetup/objects.py
PySALESetup/grain_library_directory/grain_arearatio-0.650.txt
PySALESetup/grain_library_directory/grain_arearatio-0.651.txt
PySALESetup/grain_library_directory/grain_arearatio-0.652.txt
PySALESetup/grain_library_directory/grain_arearatio-0.653.txt
PySALESetup/grain_library_directory/grain_arearatio-0.654.txt
PySALESetup/grain_library_directory/grain_arearatio-0.655.txt
PySALESetup/grain_library_directory/grain_arearatio-0.656.txt
PySALESetup/grain_library_directory/grain_arearatio-0.657.txt
PySALESetup/grain_library_directory/grain_arearatio-0.658.txt
PySALESetup/grain_library_directory/grain_arearatio-0.659.txt
PySALESetup/grain_library_directory/grain_arearatio-0.660.txt
PySALESetup/grain_library_directory/grain_arearatio-0.661.txt
PySALESetup/grain_library_directory/grain_arearatio-0.662.txt
PySALESetup/grain_library_directory/grain_arearatio-0.663.txt
PySALESetup/grain_library_directory/grain_arearatio-0.664.txt
PySALESetup/grain_library_directory/grain_arearatio-0.665.txt
PySALESetup/grain_library_directory/grain_arearatio-0.666.txt
PySALESetup/grain_library_directory/grain_arearatio-0.667.txt
PySALESetup/grain_library_directory/grain_arearatio-0.668.txt
PySALESetup/grain_library_directory/grain_arearatio-0.669.txt
PySALESetup/grain_library_directory/grain_arearatio-0.670.txt
PySALESetup/grain_library_directory/grain_arearatio-0.671.txt
PySALESetup/grain_library_directory/grain_arearatio-0.672.txt
PySALESetup/grain_library_directory/grain_arearatio-0.673.txt
PySALESetup/grain_library_directory/grain_arearatio-0.674.txt
PySALESetup/grain_library_directory/grain_arearatio-0.675.txt
PySALESetup/grain_library_directory/grain_arearatio-0.676.txt
PySALESetup/grain_library_directory/grain_arearatio-0.677.txt
PySALESetup-0.0.2.dev0.dist-info/LICENSE
PySALESetup-0.0.2.dev0.dist-info/METADATA
PySALESetup-0.0.2.dev0.dist-info/WHEEL
PySALESetup-0.0.2.dev0.dist-info/top_level.txt
PySALESetup-0.0.2.dev0.dist-info/RECORD
