Metadata-Version: 2.1
Name: PySALESetup
Version: 0.0.2.dev0
Summary: iSALE setup package
Home-page: https://github.com/jgd10/PySALESetup
Author: James Derrick
Author-email: jgd10.github@gmail.com
License: MIT
Platform: UNKNOWN
Classifier: Programming Language :: Python :: 3
Classifier: License :: OSI Approved :: MIT License
Classifier: Operating System :: OS Independent
Requires-Python: >3.6, <3.10
License-File: LICENSE
Requires-Dist: matplotlib (~=3.4.3)
Requires-Dist: numpy (~=1.21.2)
Requires-Dist: Shapely (~=1.7.0)
Requires-Dist: scipy (~=1.2.1)
